rising/__init__.py
rising/_version.py
rising/interface.py
rising/loading/__init__.py
rising/loading/collate.py
rising/loading/dataset.py
rising/loading/loader.py
rising/ops/__init__.py
rising/ops/tensor.py
rising/random/__init__.py
rising/random/abstract.py
rising/random/continuous.py
rising/random/discrete.py
rising/transforms/__init__.py
rising/transforms/abstract.py
rising/transforms/affine.py
rising/transforms/channel.py
rising/transforms/compose.py
rising/transforms/crop.py
rising/transforms/format.py
rising/transforms/intensity.py
rising/transforms/kernel.py
rising/transforms/painting.py
rising/transforms/spatial.py
rising/transforms/tensor.py
rising/transforms/utility.py
rising/transforms/functional/__init__.py
rising/transforms/functional/affine.py
rising/transforms/functional/channel.py
rising/transforms/functional/crop.py
rising/transforms/functional/intensity.py
rising/transforms/functional/painting.py
rising/transforms/functional/spatial.py
rising/transforms/functional/tensor.py
rising/transforms/functional/utility.py
rising/utils/__init__.py
rising/utils/affine.py
rising/utils/checktype.py
rising/utils/inverse.py
rising/utils/shape.py
rising/utils/torchinterp1d.py
tests/__init__.py
tests/_utils.py
tests/test_interface.py
tests/loading/__init__.py
tests/loading/test_collate.py
tests/loading/test_dataset.py
tests/loading/test_loader.py
tests/ops/__init__.py
tests/ops/test_tensor.py
tests/rand/__init__.py
tests/rand/test_abstract.py
tests/rand/test_continuous.py
tests/rand/test_discrete.py
tests/transforms/__init__.py
tests/transforms/_helpers.py
tests/transforms/test_abstract_transform.py
tests/transforms/test_affine.py
tests/transforms/test_channel.py
tests/transforms/test_compose.py
tests/transforms/test_crop.py
tests/transforms/test_format_transforms.py
tests/transforms/test_intensity_transforms.py
tests/transforms/test_kernel_transforms.py
tests/transforms/test_spatial_transforms.py
tests/transforms/test_tensor.py
rising-0.3.0.dist-info/LICENSE
rising-0.3.0.dist-info/METADATA
rising-0.3.0.dist-info/WHEEL
rising-0.3.0.dist-info/top_level.txt
rising-0.3.0.dist-info/RECORD
