Metadata-Version: 2.1
Name: rising
Version: 0.3.0
Home-page: https://github.com/PhoenixDL/rising
Author: Justus Schock, Michael Baumgartner
Author-email: justus.schock@rwth-aachen.de
License: MIT
Project-URL: Bug Tracker, https://github.com/PhoenixDL/rising/issues
Project-URL: Documentation, https://rising.rtfd.io/en/latest/
Project-URL: Source Code, https://github.com/PhoenixDL/rising
Keywords: deep learning,augmentation,transforms,pytorch,medical
Requires-Python: >=3.8
License-File: LICENSE
Requires-Dist: numpy
Requires-Dist: torch (>=1.6)
Requires-Dist: threadpoolctl
Requires-Dist: tqdm
Requires-Dist: lightning-utilities (<0.5.0,>=0.4.2)
Provides-Extra: async
Requires-Dist: dill ; extra == 'async'
